pyKVFinder/_pyKVFinder.cpython-311-darwin.so
pyKVFinder/__init__.py
pyKVFinder/utils.py
pyKVFinder/main.py
pyKVFinder/argparser.py
pyKVFinder/.dylibs/libomp.dylib
pyKVFinder/data/WimleyWhite.toml
pyKVFinder/data/EisenbergWeiss.toml
pyKVFinder/data/ZhaoLondon.toml
pyKVFinder/data/RadzickaWolfenden.toml
pyKVFinder/data/MoonFleming.toml
pyKVFinder/data/KyteDoolittle.toml
pyKVFinder/data/HessaHeijne.toml
pyKVFinder/data/vdw.dat
pyKVFinder/data/tests/ADN.pdb
pyKVFinder/data/tests/C1.pdb
pyKVFinder/data/tests/PKI.pdb
pyKVFinder/data/tests/1FMO.pdb
pyKVFinder/data/tests/1FMO.KVFinder.output.pdb
pyKVFinder/data/tests/ClO4.pdb
pyKVFinder/data/tests/1FMO.xyz
pyKVFinder/data/tests/custom-box.toml
pyKVFinder/data/tests/ADN.xyz
pyKVFinder/data/tests/residues-box.toml
pyKVFinder/grid/hydropathy.py
pyKVFinder/grid/__init__.py
pyKVFinder/grid/export.py
pyKVFinder/grid/spatial.py
pyKVFinder/grid/depth.py
pyKVFinder/grid/constitutional.py
pyKVFinder/grid/geometry.py
pyKVFinder/grid/cavity.py
pyKVFinder/grid/openings.py
pyKVFinder/grid/detect.py
pykvfinder-0.9.0.dist-info/RECORD
pykvfinder-0.9.0.dist-info/WHEEL
pykvfinder-0.9.0.dist-info/entry_points.txt
pykvfinder-0.9.0.dist-info/top_level.txt
pykvfinder-0.9.0.dist-info/METADATA
pykvfinder-0.9.0.dist-info/licenses/LICENSE
