Metadata-Version: 2.4
Name: pyKVFinder
Version: 0.9.0
Summary: Python package to detect and characterize cavities in biomolecular structures
Author: Helder V. Ribeiro-Filho, Luiz F. G. Alves, Pablo W. A. Silva, Gabriel E. Jara, Leandro O. Bortot, José G. C. Pereira, Paulo S. Lopes-de-Oliveira
Author-email: "João V. S. Guerra" <jvsguerra@gmail.com>
Maintainer-email: "João V. S. Guerra" <jvsguerra@gmail.com>
License-Expression: GPL-3.0-or-later
Project-URL: homepage, https://github.com/LBC-LNBio/pyKVFinder/
Project-URL: documentation, https://lbc-lnbio.github.io/pyKVFinder/
Project-URL: issues, https://github.com/LBC-LNBio/pyKVFinder/issues
Keywords: structural biology,proteins,biomolecules,cavity detection,cavity characterization,binding sites
Classifier: Development Status :: 4 - Beta
Classifier: Intended Audience :: Science/Research
Classifier: Programming Language :: C
Classifier: Programming Language :: Python
Classifier: Programming Language :: Python :: 3
Classifier: Programming Language :: Python :: 3.10
Classifier: Programming Language :: Python :: 3.11
Classifier: Programming Language :: Python :: 3.12
Classifier: Programming Language :: Python :: 3.13
Classifier: Programming Language :: Python :: 3.14
Classifier: Programming Language :: Python :: 3 :: Only
Classifier: Programming Language :: Python :: Implementation :: CPython
Classifier: Topic :: Software Development
Classifier: Topic :: Scientific/Engineering
Classifier: Topic :: Scientific/Engineering :: Bio-Informatics
Classifier: Topic :: Scientific/Engineering :: Chemistry
Classifier: Operating System :: Microsoft :: Windows
Classifier: Operating System :: Unix
Classifier: Operating System :: MacOS
Requires-Python: >=3.10
License-File: LICENSE
Requires-Dist: numpy<2.5.0,>=2.0.0
Requires-Dist: matplotlib<3.11.0,>=3.10.0
Requires-Dist: plotly<6.6.0,>=6.0.0
Requires-Dist: tomlkit<0.15.0,>=0.14.0
Provides-Extra: dev
Requires-Dist: pytest<9.1.0,>=9.0.0; extra == "dev"
Requires-Dist: pytest-cov<7.1.0,>=7.0.0; extra == "dev"
Requires-Dist: pytest-benchmark<5.3.0,>=5.2.0; extra == "dev"
Requires-Dist: black<26.12.0,>=26.1.0; extra == "dev"
Requires-Dist: flake8<7.4.0,>=7.3.0; extra == "dev"
Provides-Extra: docs
Requires-Dist: sphinx==8.1.3; extra == "docs"
Requires-Dist: sphinx-rtd-theme==3.1.0; extra == "docs"
Requires-Dist: sphinxcontrib-video==0.4.2; extra == "docs"
Provides-Extra: plugins
Requires-Dist: pyqt5>=5.15.11; extra == "plugins"
Dynamic: license-file
